src/__init__.py
src/mcpai.py
mo_mcp-0.1.1.dist-info/METADATA
mo_mcp-0.1.1.dist-info/WHEEL
mo_mcp-0.1.1.dist-info/entry_points.txt
mo_mcp-0.1.1.dist-info/licenses/LICENSE
mo_mcp-0.1.1.dist-info/RECORD
