Metadata-Version: 2.4
Name: mo-mcp
Version: 0.1.1
Summary: 智能命令行助手 - 基于通义千问的 MCP 协议多工具集成平台
Author-email: Andy Jin <2358155969@qq.com>
License: MIT
License-File: LICENSE
Keywords: ai,cli,command-line,mcp,qwen,tools
Classifier: Development Status :: 4 - Beta
Classifier: Intended Audience :: Developers
Classifier: License :: OSI Approved :: MIT License
Classifier: Operating System :: OS Independent
Classifier: Programming Language :: Python :: 3
Classifier: Programming Language :: Python :: 3.8
Classifier: Programming Language :: Python :: 3.9
Classifier: Programming Language :: Python :: 3.10
Classifier: Programming Language :: Python :: 3.11
Classifier: Programming Language :: Python :: 3.12
Classifier: Topic :: Software Development :: Libraries :: Python Modules
Classifier: Topic :: System :: Systems Administration
Classifier: Topic :: Utilities
Requires-Python: >=3.10
Requires-Dist: beautifulsoup4>=4.11.0
Requires-Dist: httpx>=0.24.0
Requires-Dist: lxml>=4.9.0
Requires-Dist: mcp>=1.0.0
Requires-Dist: openai>=1.0.0
Requires-Dist: pandas>=1.5.0
Requires-Dist: qrcode[pil]>=7.0.0
Provides-Extra: dev
Requires-Dist: black>=22.0.0; extra == 'dev'
Requires-Dist: flake8>=5.0.0; extra == 'dev'
Requires-Dist: mypy>=1.0.0; extra == 'dev'
Requires-Dist: pytest>=7.0.0; extra == 'dev'
